fasgan/__init__.py
fasgan/discore.py
fasgan/discriminator.py
fasgan/gencore.py
fasgan/generator.py
FasGAN-0.1.0.dist-info/LICENSE.txt
FasGAN-0.1.0.dist-info/METADATA
FasGAN-0.1.0.dist-info/WHEEL
FasGAN-0.1.0.dist-info/top_level.txt
FasGAN-0.1.0.dist-info/RECORD
