Metadata-Version: 2.1
Name: FasGAN
Version: 0.1.0
Summary: DCGAN architecture based on Fas14MNet for Image Generation
Home-page: https://github.com/DigantaD/Fas14MNet/tree/main/dcgan
Author: Diganta Dutta
Author-email: diganta.aimlos@gmail.com
License: UNKNOWN
Keywords: image generation,cnn,gan,dcgan,vanilla loss
Platform: UNKNOWN
Classifier: Development Status :: 5 - Production/Stable
Classifier: Intended Audience :: Developers
Classifier: Programming Language :: Python :: 3
Classifier: Operating System :: Unix
Classifier: Operating System :: MacOS :: MacOS X
Classifier: Operating System :: Microsoft :: Windows
Requires-Dist: torch
